MANIFEST.in
README.rst
habitual.py
requirements.txt
setup.py
habitual.egg-info/PKG-INFO
habitual.egg-info/SOURCES.txt
habitual.egg-info/dependency_links.txt
habitual.egg-info/entry_points.txt
habitual.egg-info/requires.txt
habitual.egg-info/top_level.txt