Metadata-Version: 1.1
Name: habitual
Version: 0.1.0
Summary: Send notifications for things on a fixed, repeated schedule
Home-page: https://github.com/cdown/habitual
Author: Chris Down
Author-email: chris@chrisdown.name
License: Public Domain
Keywords: cron habit tracking schedule
Platform: UNKNOWN
Classifier: Development Status :: 5 - Production/Stable
Classifier: License :: Public Domain
Classifier: Programming Language :: Python :: 3
Classifier: Topic :: Utilities
